ncafs/__init__.py
ncafs/base.py
ncafs/core.py
ncafs/tests/test_functional.py
ncafs/tests/test_unit.py
ncafs-0.2.1.dist-info/WHEEL
ncafs-0.2.1.dist-info/METADATA
ncafs-0.2.1.dist-info/RECORD
