Metadata-Version: 2.1
Name: ncafs
Version: 0.2.1
Summary: Neighborhood Component Analysis Feature Selection
Author-email: Pedro Paiva <paiva@ita.br>
Requires-Python: >=3.7
Classifier: Development Status :: 4 - Beta
Classifier: Programming Language :: Python :: 3
Classifier: License :: OSI Approved :: BSD License
Classifier: Operating System :: OS Independent
Classifier: Topic :: Scientific/Engineering :: Artificial Intelligence
Classifier: Intended Audience :: Science/Research
Requires-Dist: scikit-learn>=0.23
Requires-Dist: setuptools>=52.0.0
Requires-Dist: numpy>=1.20
Requires-Dist: scipy>=1.6
Requires-Dist: pytest>=6.0 ; extra == "dev"
Requires-Dist: notebook>=6.4 ; extra == "dev"
Requires-Dist: jupyterlab>=3.5.3 ; extra == "dev"
Project-URL: repository, https://gitlab.com/pedro.paiva/ncafs
Provides-Extra: dev
